linear_drift_detector/__init__.py
linear_drift_detector/detector.py
linear_drift_detector-0.1.0.dist-info/METADATA
linear_drift_detector-0.1.0.dist-info/WHEEL
linear_drift_detector-0.1.0.dist-info/top_level.txt
linear_drift_detector-0.1.0.dist-info/RECORD
