Metadata-Version: 2.4
Name: linear-drift-detector
Version: 0.1.0
Summary: Lightweight OLS-based concept drift detector for regression and classification
Home-page: https://github.com/SakibHasanSimanto/Linear_Drift_Detector
Author: Kazi Sakib Hasan
Author-email: simanto.alt@gmail.com
License: MIT
Classifier: Programming Language :: Python :: 3
Classifier: License :: OSI Approved :: MIT License
Classifier: Operating System :: OS Independent
Requires-Python: >=3.8
Requires-Dist: numpy
Requires-Dist: pandas
Requires-Dist: statsmodels
Requires-Dist: scipy
